MANIFEST.in
README.md
setup.cfg
setup.py
cartola_stats_cli.egg-info/PKG-INFO
cartola_stats_cli.egg-info/SOURCES.txt
cartola_stats_cli.egg-info/dependency_links.txt
cartola_stats_cli.egg-info/entry_points.txt
cartola_stats_cli.egg-info/requires.txt
cartola_stats_cli.egg-info/top_level.txt
cartolastats/__init__.py
cartolastats/__main__.py
cartolastats/cartolastats.py
cartolastats/cartola_csv/2016_atletas.csv
cartolastats/cartola_csv/2016_clubes.csv
cartolastats/cartola_csv/2016_scouts.csv
cartolastats/cartola_csv/posicoes.csv