Metadata-Version: 1.0
Name: cartola-stats-cli
Version: 0.1.0
Summary: CLI with data analysis of the game Cartola FC
Home-page: https://github.com/werberth/cartola-fc-stats
Author: werberth Vinícius
Author-email: werberth@gmail.com
License: MIT License
Keywords: cartola-fc cartola football fantasy data analysis pandas
Platform: UNKNOWN
